Metadata-Version: 2.1
Name: odoo-addon-sale-report-commitment-date
Version: 16.0.1.0.0.4
Summary: Display the commitment date on Sales Order analysis reports
Home-page: https://github.com/OCA/sale-reporting
Author: Camptocamp, Odoo Community Association (OCA)
Author-email: support@odoo-community.org
License: AGPL-3
Platform: UNKNOWN
Classifier: Programming Language :: Python
Classifier: Framework :: Odoo
Classifier: Framework :: Odoo :: 16.0
Classifier: License :: OSI Approved :: GNU Affero General Public License v3
Requires-Python: >=3.10
Requires-Dist: odoo <16.1dev,>=16.0a
